ffup/FFup.py
ffup/__init__.py
FFup-0.1.1.dist-info/LICENSE
FFup-0.1.1.dist-info/METADATA
FFup-0.1.1.dist-info/WHEEL
FFup-0.1.1.dist-info/entry_points.txt
FFup-0.1.1.dist-info/top_level.txt
FFup-0.1.1.dist-info/RECORD
