Metadata-Version: 2.1
Name: FFup
Version: 0.1.1
Summary: A tool for batch updating WebUI1111 Extensions & ComfyUI Nodes
Home-page: https://github.com/1e-2/FFup
Author: 1e-2
Classifier: Programming Language :: Python :: 3
Classifier: License :: OSI Approved :: MIT License
Classifier: Operating System :: OS Independent
License-File: LICENSE
